openapi_client/__init__.py
openapi_client/api_client.py
openapi_client/configuration.py
openapi_client/exceptions.py
openapi_client/model_utils.py
openapi_client/rest.py
openapi_client/api/__init__.py
openapi_client/api/payments_api.py
openapi_client/api/reconciliation_api.py
openapi_client/apis/__init__.py
openapi_client/model/__init__.py
openapi_client/model/exact_recurring_payment.py
openapi_client/model/exact_recurring_payment201_response.py
openapi_client/model/exact_recurring_payment400_response.py
openapi_client/model/exact_recurring_payment400_response_errors.py
openapi_client/model/exact_recurring_payment500_response.py
openapi_client/model/merchant.py
openapi_client/model/merchant_customer.py
openapi_client/model/payment403_response.py
openapi_client/model/payment403_response_errors.py
openapi_client/model/payment_conditions.py
openapi_client/model/payment_conditions_single_immediate_payment_multi.py
openapi_client/model/payment_details.py
openapi_client/model/payment_number_payments.py
openapi_client/model/payment_single_exact.py
openapi_client/model/qr_code.py
openapi_client/model/reconciliation_multi_use_link_payment200_response.py
openapi_client/model/reconciliation_multi_use_link_payment200_response_payment.py
openapi_client/model/reconciliation_multi_use_link_payment200_response_payment_conditions.py
openapi_client/model/reconciliation_multi_use_link_payment200_response_payment_details.py
openapi_client/model/reconciliation_multi_use_link_payment403_response.py
openapi_client/model/reconciliation_multi_use_link_payment404_response.py
openapi_client/model/reconciliation_multi_use_link_payment500_response.py
openapi_client/model/reconciliation_payment200_response.py
openapi_client/model/reconciliation_payment200_response_merchant.py
openapi_client/model/reconciliation_payment200_response_merchant_customer.py
openapi_client/model/reconciliation_payment200_response_payment.py
openapi_client/model/reconciliation_payment200_response_payment_details.py
kikapay_python_sdk-1.5.3.dist-info/METADATA
kikapay_python_sdk-1.5.3.dist-info/WHEEL
kikapay_python_sdk-1.5.3.dist-info/top_level.txt
kikapay_python_sdk-1.5.3.dist-info/RECORD
