Metadata-Version: 2.1
Name: kikapay-python-sdk
Version: 1.5.3
Summary: kika
Home-page: UNKNOWN
Author: OpenAPI Generator community
Author-email: info@kikapay.com
License: UNKNOWN
Keywords: OpenAPI,OpenAPI-Generator,kika
Platform: UNKNOWN
Requires-Python: >=3.6
Requires-Dist: urllib3 (>=1.25.3)
Requires-Dist: python-dateutil
Requires-Dist: nulltype
